c1gpy/__init__.py
c1gpy/fastapi_project_files/.gitignore
c1gpy/fastapi_project_files/.pre-commit-config.yaml
c1gpy/fastapi_project_files/Dockerfile
c1gpy/fastapi_project_files/README.md.template
c1gpy/fastapi_project_files/docker-compose.yml
c1gpy/fastapi_project_files/pyproject.toml.template
c1gpy/fastapi_project_files/src/__init__.py
c1gpy/fastapi_project_files/src/api_interface.py
c1gpy/fastapi_project_files/src/endpoints/__init__.py
c1gpy/fastapi_project_files/src/endpoints/router1/__init__.py
c1gpy/fastapi_project_files/src/endpoints/router1/example_endpoint.py
c1gpy/fastapi_project_files/src/endpoints/router2/__init__.py
c1gpy/fastapi_project_files/src/endpoints/router2/example_endpoint.py
c1gpy/fastapi_project_files/src/entrypoint.sh
c1gpy/fastapi_project_files/src/routers/__init__.py
c1gpy/fastapi_project_files/src/routers/router1.py
c1gpy/fastapi_project_files/src/routers/router2.py
c1gpy/fastapi_project_files/tests/__init__.py
c1gpy/fastapi_project_files/tests/test_example.py
c1gpy/google-utils.py
c1gpy/init_fastapi_project.py
c1gpy/init_streamlit_project.py
c1gpy/llm.py
c1gpy/logging.py
c1gpy/streamlit_project_files/.gitignore
c1gpy/streamlit_project_files/.pre-commit-config.yaml
c1gpy/streamlit_project_files/Dockerfile
c1gpy/streamlit_project_files/README.md.template
c1gpy/streamlit_project_files/docker-compose.yml
c1gpy/streamlit_project_files/pyproject.toml.template
c1gpy/streamlit_project_files/src/app/App.py.template
c1gpy/streamlit_project_files/src/app/__init__.py
c1gpy/streamlit_project_files/src/app/pages/1_Page_1.py
c1gpy/streamlit_project_files/src/app/pages/2_Page_2.py
c1gpy/streamlit_project_files/src/app/pages/__init__.py
c1gpy/streamlit_project_files/src/app/pages/home.py
c1gpy/streamlit_project_files/src/entrypoint.sh
c1gpy/streamlit_project_files/tests/__init__.py
c1gpy/streamlit_project_files/tests/test_example.py
c1gpy/utils.py
c1groupy-0.3.0.dist-info/METADATA
c1groupy-0.3.0.dist-info/WHEEL
c1groupy-0.3.0.dist-info/entry_points.txt
c1groupy-0.3.0.dist-info/licenses/LICENCE
c1groupy-0.3.0.dist-info/RECORD
