Metadata-Version: 2.4
Name: c1groupy
Version: 0.3.0
Summary: C1G company Python module for utilities and project setup
License-Expression: MIT
License-File: LICENCE
Author: Tim M Schendzielorz
Author-email: tim.schendzielorz@googlemail.com
Requires-Python: >=3.12, <4.0
Classifier: Programming Language :: Python :: 3
Classifier: Programming Language :: Python :: 3.12
Classifier: Programming Language :: Python :: 3.13
Classifier: Programming Language :: Python :: 3.14
Requires-Dist: argon2-cffi (>=23.0.0,<24.0.0)
Requires-Dist: google-api-python-client (>=2.0.0,<3.0.0)
Requires-Dist: google-auth (>=2.0.0,<3.0.0)
Requires-Dist: google-cloud-logging (>=3.0.0,<4.0.0)
Requires-Dist: google-cloud-secret-manager (>=2.0.0,<3.0.0)
Requires-Dist: google-cloud-storage (>=2.0.0,<3.0.0)
Requires-Dist: httpx[http2] (>=0.27.0,<1.0.0)
Requires-Dist: langfuse (>=3.6.1,<4.0.0)
Requires-Dist: rich (>=13.0.0,<14.0.0)
